clams/__init__.py
clams-0.0.5.dist-info/top_level.txt
clams-0.0.5.dist-info/RECORD
clams-0.0.5.dist-info/metadata.json
clams-0.0.5.dist-info/METADATA
clams-0.0.5.dist-info/DESCRIPTION.rst
clams-0.0.5.dist-info/pbr.json
clams-0.0.5.dist-info/WHEEL
